titangpt/__init__.py
titangpt/async_client.py
titangpt/client.py
titangpt/exceptions.py
titangpt/types.py
titangpt-0.2.1.dist-info/licenses/LICENSE
titangpt-0.2.1.dist-info/METADATA
titangpt-0.2.1.dist-info/WHEEL
titangpt-0.2.1.dist-info/top_level.txt
titangpt-0.2.1.dist-info/RECORD
